credscan/__init__.py
credscan/cli.py
credscan/analyzers/__init__.py
credscan/analyzers/entropy.py
credscan/core/__init__.py
credscan/core/engine.py
credscan/core/parser_base.py
credscan/detection/__init__.py
credscan/detection/rules.py
credscan/hooks/__init__.py
credscan/hooks/pre_commit.py
credscan/output/__init__.py
credscan/output/reporter.py
credscan/parsers/__init__.py
credscan/parsers/code_parser.py
credscan/parsers/json_parser.py
credscan/parsers/yaml_parser.py
credscan-1.0.0.dist-info/METADATA
credscan-1.0.0.dist-info/WHEEL
credscan-1.0.0.dist-info/entry_points.txt
credscan-1.0.0.dist-info/top_level.txt
credscan-1.0.0.dist-info/RECORD
